pysotope/EA/Output example_raw.csv/Log file.txt
pysotope/EA/__init__.py
pysotope/EA/base_functions.py
pysotope/EA/eaAnalyze.py
pysotope/EA/example_raw.csv
pysotope/EA/example_run.xlsx
pysotope/EA/test.csv
pysotope/EA/utils/EA_standards.csv
pysotope/EA/utils/VPD_correction.py
pysotope/EA/utils/ea_drift_correction.py
pysotope/EA/utils/import_data.py
pysotope/__init__.py
pysotope/assign_chain_length.py
pysotope/pysotope.py
pysotope/pysotope_with_3D_plot.py
pysotope/standard_editor.py
pysotope/utils/base_functions.py
pysotope/utils/config.py
pysotope/utils/corrections/drift.py
pysotope/utils/corrections/linearity.py
pysotope/utils/corrections/methanol.py
pysotope/utils/corrections/pame.py
pysotope/utils/corrections/vsmow.py
pysotope/utils/curve_fitting.py
pysotope/utils/figures.py
pysotope/utils/outliers/outliers.py
pysotope/utils/pick_chain_rt.py
pysotope/utils/queries.py
pysotope/utils/regression.py
pysotope/utils/uncertainty_and_output.py
pysotope/utils/vsmow_standards/vsmow_dC.csv
pysotope/utils/vsmow_standards/vsmow_dD.csv
pysotope-1.6.0.dist-info/LICENSE
pysotope-1.6.0.dist-info/METADATA
pysotope-1.6.0.dist-info/WHEEL
pysotope-1.6.0.dist-info/RECORD
