Metadata-Version: 2.3
Name: pysotope
Version: 1.6.0
Summary: Pysotope is an open-source package meant to processes raw data measured from the OSIBL GC-IRMS. Corrections are automatically calculated but the user must verify and confirm their application.
License: MIT
Author: Dr. Gerard Otiniano
Author-email: gerardotiniano@gmail.com
Requires-Python: >=3.9,<4.0
Classifier: License :: OSI Approved :: MIT License
Classifier: Programming Language :: Python :: 3
Classifier: Programming Language :: Python :: 3.9
Classifier: Programming Language :: Python :: 3.10
Classifier: Programming Language :: Python :: 3.11
Classifier: Programming Language :: Python :: 3.12
Classifier: Programming Language :: Python :: 3.13
